emcp/__init__.py
emcp/config.py
emcp/fs.py
emcp/main.py
emcp/shell.py
emcp/utils.py
emcp/web.py
emcp-0.3.0.dist-info/METADATA
emcp-0.3.0.dist-info/WHEEL
emcp-0.3.0.dist-info/entry_points.txt
emcp-0.3.0.dist-info/RECORD
