Metadata-Version: 2.4
Name: emcp
Version: 0.3.0
Summary: Essentials MCP server with filesystem, shell, and web tools
Project-URL: Homepage, https://github.com/slezica/emcp
Project-URL: Documentation, https://github.com/slezica/emcp#readme
Project-URL: Repository, https://github.com/slezica/emcp.git
Project-URL: Bug Tracker, https://github.com/slezica/emcp/issues
Author: Santiago Lezica
Requires-Python: >=3.10
Requires-Dist: ddgs>=9.6.0
Requires-Dist: markdownify>=1.2.0
Requires-Dist: mcp>=1.0.0
Requires-Dist: readabilipy>=0.3.0
Requires-Dist: requests>=2.32.5
